[{"name": "Articles", "children": [{"link": "http://rss.cnn.com/c/35494/f/676978/s/4b6b7977/sc/3/l/0Ledition0Bcnn0N0C20A150C110C10A0Cmiddleeast0Cegypt0Esharm0Efake0Ebomb0Edetectors0Cindex0Bhtml0Deref0Frss0Iafrica/story01.htm", "title": "Fake bomb detectors used in Egypt?"}]}, {"name": "Nouns", "children": [{"name": "sector", "size": 1}, {"name": "bomb", "size": 10}, {"name": "show", "size": 1}, {"name": "Afghanistan", "size": 1}, {"name": "years", "size": 4}, {"name": "questions", "size": 1}, {"name": "X", "size": 1}, {"name": "Department", "size": 1}, {"name": "golf", "size": 1}, {"name": "centers", "size": 1}, {"name": "staff", "size": 4}, {"name": "We", "size": 3}, {"name": "police", "size": 1}, {"name": "Business", "size": 1}, {"name": "handheld", "size": 1}, {"name": "resort", "size": 3}, {"name": "Plane", "size": 1}, {"name": "device", "size": 3}, {"name": "prison", "size": 1}, {"name": "finder", "size": 1}, {"name": "them", "size": 6}, {"name": "publicity", "size": 1}, {"name": "tourist", "size": 1}, {"name": "government", "size": 5}, {"name": "James", "size": 1}, {"name": "end", "size": 1}, {"name": "Analysis", "size": 1}, {"name": "Sheikh", "size": 3}, {"name": "tens", "size": 1}, {"name": "Paul", "size": 1}, {"name": "they", "size": 2}, {"name": "hands", "size": 1}, {"name": "judge", "size": 1}, {"name": "world", "size": 2}, {"name": "GT200", "size": 3}, {"name": "him", "size": 1}, {"name": "governments", "size": 1}, {"name": "pistol", "size": 1}, {"name": "Sharm", "size": 3}, {"name": "products", "size": 1}, {"name": "London", "size": 1}, {"name": "consultant", "size": 1}, {"name": "Inspector", "size": 1}, {"name": "el", "size": 3}, {"name": "Management", "size": 1}, {"name": "disaster", "size": 1}, {"name": "Innovation", "size": 1}, {"name": "detection", "size": 2}, {"name": "officials", "size": 1}, {"name": "export", "size": 2}, {"name": "value", "size": 1}, {"name": "invoice", "size": 1}, {"name": "images", "size": 1}, {"name": "East", "size": 1}, {"name": "Red", "size": 1}, {"name": "spokeswoman", "size": 1}, {"name": "what", "size": 1}, {"name": "pictures", "size": 1}, {"name": "novelty", "size": 1}, {"name": "protocol", "size": 1}, {"name": "label", "size": 1}, {"name": "spokesman", "size": 2}, {"name": "it", "size": 2}, {"name": "Thai", "size": 1}, {"name": "millions", "size": 1}, {"name": "issue", "size": 1}, {"name": "He", "size": 1}, {"name": "who", "size": 1}, {"name": "Variations", "size": 1}, {"name": "water", "size": 1}, {"name": "variation", "size": 1}, {"name": "situation", "size": 1}, {"name": "Heath", "size": 1}, {"name": "security", "size": 12}, {"name": "Detective", "size": 1}, {"name": "lifestyle", "size": 1}, {"name": "anything", "size": 1}, {"name": "dollars", "size": 1}, {"name": "nothing", "size": 1}, {"name": "UK", "size": 2}, {"name": "con", "size": 1}, {"name": "Hone", "size": 1}, {"name": "point", "size": 1}, {"name": "travelers", "size": 1}, {"name": "CNN", "size": 5}, {"name": "lobbies", "size": 1}, {"name": "hotels", "size": 6}, {"name": "use", "size": 3}, {"name": "Richard", "size": 1}, {"name": "army", "size": 1}, {"name": "Hotel", "size": 1}, {"name": "question", "size": 1}, {"name": "spots", "size": 1}, {"name": "tragedy", "size": 1}, {"name": "statement", "size": 2}, {"name": "Iraq", "size": 2}, {"name": "forces", "size": 2}, {"name": "hotspots", "size": 1}, {"name": "shopping", "size": 2}, {"name": "way", "size": 1}, {"name": "manufacturers", "size": 4}, {"name": "malls", "size": 1}, {"name": "hotel", "size": 2}, {"name": "Devices", "size": 1}, {"name": "locations", "size": 1}, {"name": "ADE", "size": 3}, {"name": "lives", "size": 1}, {"name": "antennas", "size": 1}, {"name": "he", "size": 4}, {"name": "case", "size": 1}, {"name": "fraud", "size": 3}, {"name": "sentencing", "size": 1}, {"name": "Office", "size": 1}, {"name": "science", "size": 2}, {"name": "appearance", "size": 1}, {"name": "devices", "size": 10}, {"name": "guards", "size": 1}, {"name": "Sea", "size": 1}, {"name": "design", "size": 2}, {"name": "piece", "size": 1}, {"name": "Tuesday", "size": 1}, {"name": "scam", "size": 1}, {"name": "wand", "size": 1}, {"name": "metal", "size": 1}, {"name": "authorities", "size": 4}, {"name": "sales", "size": 2}, {"name": "It", "size": 1}, {"name": "Edward", "size": 1}, {"name": "experts", "size": 1}, {"name": "\n\n", "size": 3}, {"name": "flight", "size": 1}, {"name": "You", "size": 1}, {"name": "casings", "size": 1}, {"name": "technology", "size": 1}, {"name": "ray", "size": 1}, {"name": "Flight", "size": 2}, {"name": "antenna", "size": 1}, {"name": "personnel", "size": 1}, {"name": "travel", "size": 2}, {"name": "concerns", "size": 2}, {"name": "machines", "size": 1}, {"name": "They", "size": 1}, {"name": "Alpha", "size": 2}, {"name": "detector", "size": 1}, {"name": "company", "size": 1}, {"name": "junk", "size": 1}, {"name": "ball", "size": 1}, {"name": "McCormick", "size": 4}, {"name": "Skills", "size": 1}, {"name": "advice", "size": 1}, {"name": "measures", "size": 2}, {"name": "British", "size": 1}, {"name": "Foreign", "size": 1}, {"name": "chance", "size": 1}, {"name": "brands", "size": 1}, {"name": "Biddiss", "size": 3}, {"name": "Metrojet", "size": 1}, {"name": "court", "size": 1}, {"name": "man", "size": 1}, {"name": "shortcomings", "size": 1}, {"name": "Egypt", "size": 1}, {"name": "detectors", "size": 6}, {"name": "dog", "size": 1}, {"name": "Middle", "size": 1}, {"name": "part", "size": 1}, {"name": "components", "size": 1}, {"name": "wake", "size": 2}, {"name": "physics", "size": 1}, {"name": "Saturday", "size": 1}, {"name": "laws", "size": 1}]}, {"name": "Geo-Political Entities", "children": [{"name": "Afghanistan", "size": 1}, {"name": "Egypt", "size": 1}, {"name": "London", "size": 1}, {"name": "UK", "size": 2}, {"name": "Sharm el-Sheikh", "size": 3}, {"name": "Iraq", "size": 2}]}, {"name": "Events", "children": []}, {"name": "Products", "children": [{"name": "GT200", "size": 1}, {"name": "Flight 9268", "size": 1}]}, {"name": "Organizations", "children": [{"name": "CNN", "size": 5}, {"name": "Department for Business", "size": 1}, {"name": "the British Foreign Office", "size": 1}]}, {"name": "Languages", "children": []}, {"name": "Dates", "children": [{"name": "24 years", "size": 1}, {"name": "10 years", "size": 1}, {"name": "Tuesday", "size": 1}, {"name": "last Saturday", "size": 1}, {"name": "nearly three years", "size": 1}, {"name": "2010", "size": 1}, {"name": "2013", "size": 3}, {"name": "recent years", "size": 1}]}, {"name": "Cardinal Numbers", "children": [{"name": "one", "size": 1}, {"name": "Two", "size": 1}, {"name": "two", "size": 2}, {"name": "One", "size": 1}, {"name": "four", "size": 1}, {"name": "6", "size": 2}, {"name": "224", "size": 1}, {"name": "tens of millions", "size": 1}]}, {"name": "Times", "children": []}, {"name": "Nationalities, Organizations, Religions, and Political Parties", "children": [{"name": "Thai", "size": 1}, {"name": "British", "size": 8}, {"name": "Egyptian", "size": 2}]}, {"name": "Ordinal Numbers", "children": []}, {"name": "Works of Art", "children": []}, {"name": "Quantities", "children": []}, {"name": "Percents", "children": []}, {"name": "Money", "children": [{"name": "more than $38 million", "size": 1}]}, {"name": "Locations", "children": [{"name": "the Red Sea", "size": 1}]}, {"name": "Laws", "children": []}, {"name": "Facilities", "children": []}, {"name": "People", "children": [{"name": "McCormick", "size": 3}, {"name": "Edward Heath", "size": 1}, {"name": "Paul Biddiss", "size": 1}, {"name": "Richard Hone", "size": 1}, {"name": "Biddiss", "size": 1}, {"name": "James McCormick", "size": 1}]}]